big/__init__.py
big/all.py
big/boundinnerclass.py
big/builtin.py
big/file.py
big/graph.py
big/heap.py
big/itertools.py
big/log.py
big/scheduler.py
big/state.py
big/text.py
big/time.py
big-0.10.dist-info/LICENSE
big-0.10.dist-info/WHEEL
big-0.10.dist-info/METADATA
big-0.10.dist-info/RECORD
