Metadata-Version: 2.1
Name: big
Version: 0.10
Summary: The big package is a grab-bag of cool code for use in your programs.
Author-email: Larry Hastings <larry@hastings.org>
Requires-Python: >=3.6
Classifier: Intended Audience :: Developers
Classifier: License :: OSI Approved :: MIT License
Classifier: Programming Language :: Python :: 3
Classifier: Programming Language :: Python :: 3.6
Classifier: Programming Language :: Python :: 3.7
Classifier: Programming Language :: Python :: 3.8
Classifier: Programming Language :: Python :: 3.9
Classifier: Programming Language :: Python :: 3.10
Classifier: Programming Language :: Python :: 3.11
Classifier: Programming Language :: Python :: 3.12
Requires-Dist: python-dateutil ; extra == "test"
Requires-Dist: regex ; extra == "test"
Requires-Dist: inflect ; extra == "test"
Requires-Dist: python-dateutil ; extra == "time"
Project-URL: Source, https://github.com/larryhastings/big/
Provides-Extra: test
Provides-Extra: time
